bwb/__init__.py
bwb/bwb.py
bwb/common.py
bwb/jason.py
bwb/molly.py
bwb/tanner.py
bwb/tdev.py
bwb-3.0.0.dist-info/METADATA
bwb-3.0.0.dist-info/WHEEL
bwb-3.0.0.dist-info/top_level.txt
bwb-3.0.0.dist-info/RECORD
