Metadata-Version: 2.1
Name: bwb
Version: 3.0.0
Summary: bwb
Home-page: https://qotmail.com
Author: bwb
Author-email: bwbpy@qotmail.com
License: QPL.txt
Platform: UNKNOWN
Requires-Dist: base58
Requires-Dist: cryptography
